{"nodes": [{"id": "docs_catalog_admin_design_import_design", "label": "Catalog Admin \u2014 Add & Import Products Design", "file_type": "document", "source_file": "docs/catalog-admin-design.md", "source_location": null, "source_url": null, "captured_at": null, "author": null, "contributor": null}], "edges": [{"source": "docs_catalog_admin_design_import_design", "target": "docs_phase3_multi_brand_design_multi_brand_arch", "relation": "references", "confidence": "EXTRACTED", "confidence_score": 1.0, "source_file": "docs/catalog-admin-design.md", "source_location": null, "weight": 1.0}, {"source": "docs_catalog_admin_design_import_design", "target": "docs_specs_seed_data_seed_spec", "relation": "references", "confidence": "EXTRACTED", "confidence_score": 1.0, "source_file": "docs/catalog-admin-design.md", "source_location": null, "weight": 1.0}, {"source": "docs_catalog_admin_design_import_design", "target": "docs_specs_seed_data_seed_spec", "relation": "semantically_similar_to", "confidence": "INFERRED", "confidence_score": 0.85, "source_file": "docs/catalog-admin-design.md", "source_location": null, "weight": 1.0}], "hyperedges": []}