{"nodes": [{"id": "design_design_brief_phase1_brief", "label": "Phase 1 Design Brief", "file_type": "document", "source_file": "design/design-brief.md", "source_location": null, "source_url": null, "captured_at": null, "author": null, "contributor": null}], "edges": [{"source": "design_design_brief_phase1_brief", "target": "docs_problem_statement_business_context", "relation": "references", "confidence": "EXTRACTED", "confidence_score": 1.0, "source_file": "design/design-brief.md", "source_location": null, "weight": 1.0}, {"source": "design_design_brief_phase1_brief", "target": "docs_specs_salesman_app_mobile_spec", "relation": "references", "confidence": "EXTRACTED", "confidence_score": 1.0, "source_file": "design/design-brief.md", "source_location": null, "weight": 1.0}, {"source": "design_design_brief_phase1_brief", "target": "docs_specs_accountant_dashboard_dashboard_spec", "relation": "references", "confidence": "EXTRACTED", "confidence_score": 1.0, "source_file": "design/design-brief.md", "source_location": null, "weight": 1.0}, {"source": "design_design_brief_phase1_brief", "target": "docs_future_plans_parking_lot", "relation": "references", "confidence": "EXTRACTED", "confidence_score": 1.0, "source_file": "design/design-brief.md", "source_location": null, "weight": 1.0}], "hyperedges": []}